mathkeyboardengine/AscendingBranchingNode.py
mathkeyboardengine/BranchingNode.py
mathkeyboardengine/DecimalSeparatorNode.py
mathkeyboardengine/DescendingBranchingNode.py
mathkeyboardengine/DigitNode.py
mathkeyboardengine/KeyboardMemory.py
mathkeyboardengine/LatexConfiguration.py
mathkeyboardengine/LatexParserConfiguration.py
mathkeyboardengine/LeafNode.py
mathkeyboardengine/MatrixNode.py
mathkeyboardengine/PartOfNumberWithDigits.py
mathkeyboardengine/Placeholder.py
mathkeyboardengine/RoundBracketsNode.py
mathkeyboardengine/StandardBranchingNode.py
mathkeyboardengine/StandardLeafNode.py
mathkeyboardengine/TreeNode.py
mathkeyboardengine/__init__.py
mathkeyboardengine/delete_left.py
mathkeyboardengine/delete_right.py
mathkeyboardengine/delete_selection.py
mathkeyboardengine/enter_selection_mode.py
mathkeyboardengine/get_edit_mode_latex.py
mathkeyboardengine/get_view_mode_latex.py
mathkeyboardengine/in_selection_mode.py
mathkeyboardengine/insert.py
mathkeyboardengine/insert_with_encapsulate_current.py
mathkeyboardengine/insert_with_encapsulate_selection.py
mathkeyboardengine/insert_with_encapsulate_selection_and_previous.py
mathkeyboardengine/leave_selection_mode.py
mathkeyboardengine/move_down.py
mathkeyboardengine/move_left.py
mathkeyboardengine/move_right.py
mathkeyboardengine/move_up.py
mathkeyboardengine/parse_latex.py
mathkeyboardengine/select_left.py
mathkeyboardengine/select_right.py
mathkeyboardengine/_helpers/__init__.py
mathkeyboardengine/_helpers/coalesce.py
mathkeyboardengine/_helpers/concat_latex.py
mathkeyboardengine/_helpers/delete_outer_branching_node_but_not_its_contents.py
mathkeyboardengine/_helpers/encapsulate.py
mathkeyboardengine/_helpers/encapsulate_all_parts_of_number_with_digits_left_of_index.py
mathkeyboardengine/_helpers/ends_with_latex_command.py
mathkeyboardengine/_helpers/first_after_or_none.py
mathkeyboardengine/_helpers/first_before_or_none.py
mathkeyboardengine/_helpers/first_or_none.py
mathkeyboardengine-1.0.0.dist-info/LICENSE.txt
mathkeyboardengine-1.0.0.dist-info/METADATA
mathkeyboardengine-1.0.0.dist-info/WHEEL
mathkeyboardengine-1.0.0.dist-info/top_level.txt
mathkeyboardengine-1.0.0.dist-info/RECORD
