Metadata-Version: 2.1
Name: mathkeyboardengine
Version: 1.0.0
Summary: MathKeyboardEngine provides the logic for a highly customizable virtual math keyboard. It is intended for use together with any LaTeX typesetting library.
Home-page: https://github.com/MathKeyboardEngine/MathKeyboardEngine.Python
Author: MathKeyboardEngine
Author-email: symbolinker@gmail.com
License: 0BSD
Platform: UNKNOWN
Classifier: Development Status :: 5 - Production/Stable
Classifier: Programming Language :: Python
Classifier: Programming Language :: Python :: 3.8
Classifier: Programming Language :: Python :: 3.9
Classifier: Programming Language :: Python :: 3.10
Classifier: Programming Language :: Python :: 3.11
Classifier: Programming Language :: Python :: 3.12
Classifier: Programming Language :: Python :: 3.13
Classifier: Operating System :: OS Independent
